django_scylla/__init__.py
django_scylla/apps.py
django_scylla/base.py
django_scylla/client.py
django_scylla/constraints.py
django_scylla/cql/__init__.py
django_scylla/cql/compiler.py
django_scylla/cql/expressions.py
django_scylla/cql/query.py
django_scylla/cql/queryset.py
django_scylla/cql/where.py
django_scylla/creation.py
django_scylla/cursor.py
django_scylla/database.py
django_scylla/features.py
django_scylla/introspection.py
django_scylla/models.py
django_scylla/operations.py
django_scylla/options.py
django_scylla/schema.py
django_scylla/validation.py
django_scylla-0.0.10.dist-info/LICENSE.rst
django_scylla-0.0.10.dist-info/WHEEL
django_scylla-0.0.10.dist-info/METADATA
django_scylla-0.0.10.dist-info/RECORD
