Metadata-Version: 2.1
Name: django-scylla
Version: 0.0.10
Summary: Django Scylla
Home-page: https://github.com/r4fek/django-scylla
License: MIT
Author: Rafał Furmański
Author-email: r.furmanski@gmail.com
Requires-Python: >=3.8,<4.0
Classifier: Development Status :: 3 - Alpha
Classifier: License :: OSI Approved :: MIT License
Classifier: Programming Language :: Python :: 3
Classifier: Programming Language :: Python :: 3.8
Classifier: Programming Language :: Python :: 3.9
Classifier: Programming Language :: Python :: 3.10
Classifier: Programming Language :: Python :: 3.11
Classifier: Programming Language :: Python :: 3.10
Classifier: Programming Language :: Python :: 3.8
Classifier: Programming Language :: Python :: 3.9
Requires-Dist: django (>=3.1,<5.0)
Requires-Dist: scylla-driver (>=3.25,<4.0)
Project-URL: Changelog, https://github.com/r4fek/django-scylla/releases
Project-URL: Documentation, https://django-scylla.readthedocs.io
Project-URL: Repository, https://github.com/r4fek/django-scylla
